compyss/__init__.py
compyss/compass.py
compyss/image.py
compyss/decoders/__init__.py
compyss/decoders/hough.py
compyss/sources/__init__.py
compyss/sources/arena_sdk.py
compyss/sources/file.py
compyss/sources/image_source.py
compyss-1.1.1.dist-info/LICENSE.md
compyss-1.1.1.dist-info/METADATA
compyss-1.1.1.dist-info/WHEEL
compyss-1.1.1.dist-info/top_level.txt
compyss-1.1.1.dist-info/RECORD
