Metadata-Version: 2.1
Name: compyss
Version: 1.1.1
Summary: A tool built for analysing skylight polarization patterns.
Home-page: https://github.com/benjaminpotter/compyss
Author: Ben Potter
Author-email: Benjamin Potter <baffqd@gmail.com>
Project-URL: Homepage, https://github.com/benjaminpotter/compyss
Project-URL: Bug Tracker, https://github.com/benjaminpotter/compyss/issues
Classifier: Programming Language :: Python :: 3
Classifier: License :: OSI Approved :: GNU General Public License v3 (GPLv3)
Classifier: Operating System :: OS Independent
Requires-Python: >=3.11.4
License-File: LICENSE.md
